botoprune/__init__.py
botoprune/_implementation.py
botoprune/remove.py
botoprune/whitelist.py
botoprune-1.1.0.dist-info/licenses/LICENSE
botoprune-1.1.0.dist-info/METADATA
botoprune-1.1.0.dist-info/WHEEL
botoprune-1.1.0.dist-info/top_level.txt
botoprune-1.1.0.dist-info/RECORD
