Metadata-Version: 2.4
Name: botoprune
Version: 1.1.0
Summary: Reduce the installed size of botocore by removing unnecessary AWS api data.
Author: Evan Parker
Maintainer: Evan Parker
License-Expression: Apache-2.0
Project-URL: Homepage, https://github.com/eap/botoprune
Project-URL: Repository, https://github.com/eap/botoprune
Project-URL: Issues, https://github.com/eap/botoprune/issues
Keywords: botocore,boto3,boto-prune,botoprune,boto-trim,bototrim
Classifier: Development Status :: 4 - Beta
Classifier: Operating System :: OS Independent
Classifier: Operating System :: POSIX
Classifier: Operating System :: POSIX :: Linux
Classifier: Programming Language :: Python
Classifier: Programming Language :: Python :: 3
Classifier: Programming Language :: Python :: 3.9
Classifier: Programming Language :: Python :: 3.10
Classifier: Programming Language :: Python :: 3.11
Classifier: Programming Language :: Python :: 3.12
Classifier: Programming Language :: Python :: 3.13
Classifier: Programming Language :: Python :: 3 :: Only
Classifier: Topic :: Software Development :: Build Tools
Classifier: Topic :: Software Development :: Libraries
Classifier: Topic :: Software Development :: Libraries :: Python Modules
Requires-Python: >=3.9
License-File: LICENSE
Requires-Dist: botocore>=1.23.26
Provides-Extra: test
Requires-Dist: pytest>=6.0; extra == "test"
Requires-Dist: flake8>=7.3.0; extra == "test"
Requires-Dist: Flake8-pyproject>=1.2.3; extra == "test"
Dynamic: license-file
